[
  {
    "symbol": "ADA",
    "timestamp": "2025-02-26T00:00:00",
    "open": 0.683198,
    "high": 0.686126,
    "low": 0.675852,
    "close": 0.676097,
    "volume": 0.0,
    "interval": "1h"
  },
  {
    "symbol": "ADA",
    "timestamp": "2025-02-26T01:00:00",
    "open": 0.675992,
    "high": 0.682934,
    "low": 0.675992,
    "close": 0.680779,
    "volume": 0.0,
    "interval": "1h"
  },
  {
    "symbol": "ADA",
    "timestamp": "2025-02-26T02:00:00",
    "open": 0.68075,
    "high": 0.690668,
    "low": 0.677006,
    "close": 0.688408,
    "volume": 0.0,
    "interval": "1h"
  },
  {
    "symbol": "ADA",
    "timestamp": "2025-02-26T03:00:00",
    "open": 0.688484,
    "high": 0.695498,
    "low": 0.688061,
    "close": 0.689592,
    "volume": 0.0,
    "interval": "1h"
  },
  {
    "symbol": "ADA",
    "timestamp": "2025-02-26T04:00:00",
    "open": 0.689617,
    "high": 0.694391,
    "low": 0.686908,
    "close": 0.687897,
    "volume": 0.0,
    "interval": "1h"
  },
  {
    "symbol": "ADA",
    "timestamp": "2025-02-26T05:00:00",
    "open": 0.687905,
    "high": 0.689404,
    "low": 0.680319,
    "close": 0.680598,
    "volume": 0.0,
    "interval": "1h"
  },
  {
    "symbol": "ADA",
    "timestamp": "2025-02-26T06:00:00",
    "open": 0.680684,
    "high": 0.687447,
    "low": 0.680061,
    "close": 0.687264,
    "volume": 0.0,
    "interval": "1h"
  },
  {
    "symbol": "ADA",
    "timestamp": "2025-02-26T07:00:00",
    "open": 0.687259,
    "high": 0.688872,
    "low": 0.676809,
    "close": 0.682014,
    "volume": 0.0,
    "interval": "1h"
  },
  {
    "symbol": "ADA",
    "timestamp": "2025-02-26T08:00:00",
    "open": 0.682025,
    "high": 0.683153,
    "low": 0.673885,
    "close": 0.678356,
    "volume": 0.0,
    "interval": "1h"
  },
  {
    "symbol": "ADA",
    "timestamp": "2025-02-26T09:00:00",
    "open": 0.678543,
    "high": 0.689945,
    "low": 0.67691,
    "close": 0.688734,
    "volume": 0.0,
    "interval": "1h"
  },
  {
    "symbol": "ADA",
    "timestamp": "2025-02-26T10:00:00",
    "open": 0.688518,
    "high": 0.689901,
    "low": 0.680934,
    "close": 0.68847,
    "volume": 0.0,
    "interval": "1h"
  },
  {
    "symbol": "ADA",
    "timestamp": "2025-02-26T11:00:00",
    "open": 0.688463,
    "high": 0.690169,
    "low": 0.679672,
    "close": 0.680135,
    "volume": 0.0,
    "interval": "1h"
  },
  {
    "symbol": "ADA",
    "timestamp": "2025-02-26T12:00:00",
    "open": 0.680231,
    "high": 0.681191,
    "low": 0.663875,
    "close": 0.668279,
    "volume": 0.0,
    "interval": "1h"
  },
  {
    "symbol": "ADA",
    "timestamp": "2025-02-26T13:00:00",
    "open": 0.668209,
    "high": 0.67181,
    "low": 0.663824,
    "close": 0.66528,
    "volume": 0.0,
    "interval": "1h"
  },
  {
    "symbol": "ADA",
    "timestamp": "2025-02-26T14:00:00",
    "open": 0.665257,
    "high": 0.680574,
    "low": 0.655371,
    "close": 0.677194,
    "volume": 0.0,
    "interval": "1h"
  },
  {
    "symbol": "ADA",
    "timestamp": "2025-02-26T15:00:00",
    "open": 0.677437,
    "high": 0.687743,
    "low": 0.676212,
    "close": 0.677211,
    "volume": 0.0,
    "interval": "1h"
  },
  {
    "symbol": "ADA",
    "timestamp": "2025-02-26T16:00:00",
    "open": 0.677348,
    "high": 0.679308,
    "low": 0.664606,
    "close": 0.67192,
    "volume": 0.0,
    "interval": "1h"
  },
  {
    "symbol": "ADA",
    "timestamp": "2025-02-26T17:00:00",
    "open": 0.672051,
    "high": 0.674182,
    "low": 0.653537,
    "close": 0.657385,
    "volume": 0.0,
    "interval": "1h"
  },
  {
    "symbol": "ADA",
    "timestamp": "2025-02-26T18:00:00",
    "open": 0.65709,
    "high": 0.661838,
    "low": 0.637472,
    "close": 0.641638,
    "volume": 0.0,
    "interval": "1h"
  },
  {
    "symbol": "ADA",
    "timestamp": "2025-02-26T19:00:00",
    "open": 0.641569,
    "high": 0.647814,
    "low": 0.63655,
    "close": 0.640225,
    "volume": 0.0,
    "interval": "1h"
  },
  {
    "symbol": "ADA",
    "timestamp": "2025-02-26T20:00:00",
    "open": 0.640289,
    "high": 0.657049,
    "low": 0.631224,
    "close": 0.654972,
    "volume": 0.0,
    "interval": "1h"
  },
  {
    "symbol": "ADA",
    "timestamp": "2025-02-26T21:00:00",
    "open": 0.654887,
    "high": 0.657641,
    "low": 0.644975,
    "close": 0.652957,
    "volume": 0.0,
    "interval": "1h"
  },
  {
    "symbol": "ADA",
    "timestamp": "2025-02-26T22:00:00",
    "open": 0.653009,
    "high": 0.663362,
    "low": 0.650201,
    "close": 0.651406,
    "volume": 0.0,
    "interval": "1h"
  },
  {
    "symbol": "ADA",
    "timestamp": "2025-02-26T23:00:00",
    "open": 0.651338,
    "high": 0.655737,
    "low": 0.644617,
    "close": 0.647462,
    "volume": 0.0,
    "interval": "1h"
  },
  {
    "symbol": "ADA",
    "timestamp": "2025-02-27T00:00:00",
    "open": 0.647578,
    "high": 0.65185,
    "low": 0.641777,
    "close": 0.64666,
    "volume": 0.0,
    "interval": "1h"
  },
  {
    "symbol": "ADA",
    "timestamp": "2025-02-27T01:00:00",
    "open": 0.646714,
    "high": 0.65785,
    "low": 0.641373,
    "close": 0.652809,
    "volume": 0.0,
    "interval": "1h"
  },
  {
    "symbol": "ADA",
    "timestamp": "2025-02-27T02:00:00",
    "open": 0.65281,
    "high": 0.663,
    "low": 0.650804,
    "close": 0.653093,
    "volume": 0.0,
    "interval": "1h"
  },
  {
    "symbol": "ADA",
    "timestamp": "2025-02-27T03:00:00",
    "open": 0.653069,
    "high": 0.659899,
    "low": 0.651508,
    "close": 0.65812,
    "volume": 0.0,
    "interval": "1h"
  },
  {
    "symbol": "ADA",
    "timestamp": "2025-02-27T04:00:00",
    "open": 0.658096,
    "high": 0.661942,
    "low": 0.652057,
    "close": 0.656112,
    "volume": 0.0,
    "interval": "1h"
  },
  {
    "symbol": "ADA",
    "timestamp": "2025-02-27T05:00:00",
    "open": 0.656025,
    "high": 0.664308,
    "low": 0.655491,
    "close": 0.662967,
    "volume": 0.0,
    "interval": "1h"
  },
  {
    "symbol": "ADA",
    "timestamp": "2025-02-27T06:00:00",
    "open": 0.662961,
    "high": 0.67026,
    "low": 0.661189,
    "close": 0.668549,
    "volume": 0.0,
    "interval": "1h"
  },
  {
    "symbol": "ADA",
    "timestamp": "2025-02-27T07:00:00",
    "open": 0.668574,
    "high": 0.672047,
    "low": 0.666025,
    "close": 0.668766,
    "volume": 0.0,
    "interval": "1h"
  },
  {
    "symbol": "ADA",
    "timestamp": "2025-02-27T08:00:00",
    "open": 0.668764,
    "high": 0.669392,
    "low": 0.66161,
    "close": 0.665104,
    "volume": 0.0,
    "interval": "1h"
  },
  {
    "symbol": "ADA",
    "timestamp": "2025-02-27T09:00:00",
    "open": 0.665093,
    "high": 0.671567,
    "low": 0.664938,
    "close": 0.669132,
    "volume": 0.0,
    "interval": "1h"
  },
  {
    "symbol": "ADA",
    "timestamp": "2025-02-27T10:00:00",
    "open": 0.669132,
    "high": 0.678338,
    "low": 0.667817,
    "close": 0.67803,
    "volume": 0.0,
    "interval": "1h"
  },
  {
    "symbol": "ADA",
    "timestamp": "2025-02-27T11:00:00",
    "open": 0.678067,
    "high": 0.678707,
    "low": 0.671784,
    "close": 0.675618,
    "volume": 0.0,
    "interval": "1h"
  },
  {
    "symbol": "ADA",
    "timestamp": "2025-02-27T12:00:00",
    "open": 0.675629,
    "high": 0.679675,
    "low": 0.671015,
    "close": 0.67367,
    "volume": 0.0,
    "interval": "1h"
  },
  {
    "symbol": "ADA",
    "timestamp": "2025-02-27T13:00:00",
    "open": 0.673695,
    "high": 0.678014,
    "low": 0.669048,
    "close": 0.671148,
    "volume": 0.0,
    "interval": "1h"
  },
  {
    "symbol": "ADA",
    "timestamp": "2025-02-27T14:00:00",
    "open": 0.671156,
    "high": 0.676004,
    "low": 0.662101,
    "close": 0.662299,
    "volume": 0.0,
    "interval": "1h"
  },
  {
    "symbol": "ADA",
    "timestamp": "2025-02-27T15:00:00",
    "open": 0.662101,
    "high": 0.669621,
    "low": 0.65777,
    "close": 0.665886,
    "volume": 0.0,
    "interval": "1h"
  },
  {
    "symbol": "ADA",
    "timestamp": "2025-02-27T16:00:00",
    "open": 0.665977,
    "high": 0.668717,
    "low": 0.654888,
    "close": 0.655893,
    "volume": 0.0,
    "interval": "1h"
  },
  {
    "symbol": "ADA",
    "timestamp": "2025-02-27T17:00:00",
    "open": 0.656003,
    "high": 0.657975,
    "low": 0.65,
    "close": 0.655103,
    "volume": 0.0,
    "interval": "1h"
  },
  {
    "symbol": "ADA",
    "timestamp": "2025-02-27T18:00:00",
    "open": 0.655056,
    "high": 0.661104,
    "low": 0.654354,
    "close": 0.65631,
    "volume": 0.0,
    "interval": "1h"
  },
  {
    "symbol": "ADA",
    "timestamp": "2025-02-27T19:00:00",
    "open": 0.656398,
    "high": 0.656448,
    "low": 0.643863,
    "close": 0.646714,
    "volume": 0.0,
    "interval": "1h"
  },
  {
    "symbol": "ADA",
    "timestamp": "2025-02-27T20:00:00",
    "open": 0.646808,
    "high": 0.647488,
    "low": 0.629188,
    "close": 0.63378,
    "volume": 0.0,
    "interval": "1h"
  },
  {
    "symbol": "ADA",
    "timestamp": "2025-02-27T21:00:00",
    "open": 0.633707,
    "high": 0.643197,
    "low": 0.6263,
    "close": 0.642182,
    "volume": 0.0,
    "interval": "1h"
  },
  {
    "symbol": "ADA",
    "timestamp": "2025-02-27T22:00:00",
    "open": 0.64217,
    "high": 0.648911,
    "low": 0.635485,
    "close": 0.648379,
    "volume": 0.0,
    "interval": "1h"
  },
  {
    "symbol": "ADA",
    "timestamp": "2025-02-27T23:00:00",
    "open": 0.648091,
    "high": 0.648995,
    "low": 0.643201,
    "close": 0.645176,
    "volume": 0.0,
    "interval": "1h"
  },
  {
    "symbol": "ADA",
    "timestamp": "2025-02-28T00:00:00",
    "open": 0.645409,
    "high": 0.646722,
    "low": 0.638001,
    "close": 0.638001,
    "volume": 0.0,
    "interval": "1h"
  },
  {
    "symbol": "ADA",
    "timestamp": "2025-02-28T01:00:00",
    "open": 0.638001,
    "high": 0.640199,
    "low": 0.610992,
    "close": 0.612985,
    "volume": 0.0,
    "interval": "1h"
  },
  {
    "symbol": "ADA",
    "timestamp": "2025-02-28T02:00:00",
    "open": 0.612837,
    "high": 0.621235,
    "low": 0.60155,
    "close": 0.608798,
    "volume": 0.0,
    "interval": "1h"
  },
  {
    "symbol": "ADA",
    "timestamp": "2025-02-28T03:00:00",
    "open": 0.608891,
    "high": 0.616421,
    "low": 0.6,
    "close": 0.602297,
    "volume": 0.0,
    "interval": "1h"
  },
  {
    "symbol": "ADA",
    "timestamp": "2025-02-28T04:00:00",
    "open": 0.602535,
    "high": 0.603307,
    "low": 0.590576,
    "close": 0.598374,
    "volume": 0.0,
    "interval": "1h"
  },
  {
    "symbol": "ADA",
    "timestamp": "2025-02-28T05:00:00",
    "open": 0.598347,
    "high": 0.601005,
    "low": 0.587998,
    "close": 0.595782,
    "volume": 0.0,
    "interval": "1h"
  },
  {
    "symbol": "ADA",
    "timestamp": "2025-02-28T06:00:00",
    "open": 0.595958,
    "high": 0.59785,
    "low": 0.581366,
    "close": 0.58869,
    "volume": 0.0,
    "interval": "1h"
  },
  {
    "symbol": "ADA",
    "timestamp": "2025-02-28T07:00:00",
    "open": 0.588522,
    "high": 0.598344,
    "low": 0.588321,
    "close": 0.592973,
    "volume": 0.0,
    "interval": "1h"
  },
  {
    "symbol": "ADA",
    "timestamp": "2025-02-28T08:00:00",
    "open": 0.592961,
    "high": 0.59644,
    "low": 0.580163,
    "close": 0.59566,
    "volume": 0.0,
    "interval": "1h"
  },
  {
    "symbol": "ADA",
    "timestamp": "2025-02-28T09:00:00",
    "open": 0.595671,
    "high": 0.608249,
    "low": 0.593976,
    "close": 0.605158,
    "volume": 0.0,
    "interval": "1h"
  },
  {
    "symbol": "ADA",
    "timestamp": "2025-02-28T10:00:00",
    "open": 0.605496,
    "high": 0.606776,
    "low": 0.593522,
    "close": 0.594815,
    "volume": 0.0,
    "interval": "1h"
  },
  {
    "symbol": "ADA",
    "timestamp": "2025-02-28T11:00:00",
    "open": 0.594823,
    "high": 0.60489,
    "low": 0.593991,
    "close": 0.599428,
    "volume": 0.0,
    "interval": "1h"
  },
  {
    "symbol": "ADA",
    "timestamp": "2025-02-28T12:00:00",
    "open": 0.599344,
    "high": 0.60371,
    "low": 0.594325,
    "close": 0.602644,
    "volume": 0.0,
    "interval": "1h"
  },
  {
    "symbol": "ADA",
    "timestamp": "2025-02-28T13:00:00",
    "open": 0.602569,
    "high": 0.619387,
    "low": 0.601913,
    "close": 0.614513,
    "volume": 0.0,
    "interval": "1h"
  },
  {
    "symbol": "ADA",
    "timestamp": "2025-02-28T14:00:00",
    "open": 0.614465,
    "high": 0.626663,
    "low": 0.612782,
    "close": 0.618858,
    "volume": 0.0,
    "interval": "1h"
  },
  {
    "symbol": "ADA",
    "timestamp": "2025-02-28T15:00:00",
    "open": 0.618816,
    "high": 0.637143,
    "low": 0.618279,
    "close": 0.631253,
    "volume": 0.0,
    "interval": "1h"
  },
  {
    "symbol": "ADA",
    "timestamp": "2025-02-28T16:00:00",
    "open": 0.631255,
    "high": 0.636903,
    "low": 0.62448,
    "close": 0.631973,
    "volume": 0.0,
    "interval": "1h"
  },
  {
    "symbol": "ADA",
    "timestamp": "2025-02-28T17:00:00",
    "open": 0.631897,
    "high": 0.634161,
    "low": 0.625848,
    "close": 0.626634,
    "volume": 0.0,
    "interval": "1h"
  },
  {
    "symbol": "ADA",
    "timestamp": "2025-02-28T18:00:00",
    "open": 0.626624,
    "high": 0.639329,
    "low": 0.625336,
    "close": 0.633348,
    "volume": 0.0,
    "interval": "1h"
  },
  {
    "symbol": "ADA",
    "timestamp": "2025-02-28T19:00:00",
    "open": 0.63328,
    "high": 0.637415,
    "low": 0.630309,
    "close": 0.634533,
    "volume": 0.0,
    "interval": "1h"
  },
  {
    "symbol": "ADA",
    "timestamp": "2025-02-28T20:00:00",
    "open": 0.634631,
    "high": 0.635742,
    "low": 0.626668,
    "close": 0.631349,
    "volume": 0.0,
    "interval": "1h"
  },
  {
    "symbol": "ADA",
    "timestamp": "2025-02-28T21:00:00",
    "open": 0.631271,
    "high": 0.636992,
    "low": 0.629418,
    "close": 0.631627,
    "volume": 0.0,
    "interval": "1h"
  },
  {
    "symbol": "ADA",
    "timestamp": "2025-02-28T22:00:00",
    "open": 0.631619,
    "high": 0.633797,
    "low": 0.626922,
    "close": 0.629273,
    "volume": 0.0,
    "interval": "1h"
  },
  {
    "symbol": "ADA",
    "timestamp": "2025-02-28T23:00:00",
    "open": 0.62924,
    "high": 0.635376,
    "low": 0.628242,
    "close": 0.632757,
    "volume": 0.0,
    "interval": "1h"
  },
  {
    "symbol": "ADA",
    "timestamp": "2025-03-01T00:00:00",
    "open": 0.632766,
    "high": 0.636514,
    "low": 0.628421,
    "close": 0.629254,
    "volume": 0.0,
    "interval": "1h"
  },
  {
    "symbol": "ADA",
    "timestamp": "2025-03-01T01:00:00",
    "open": 0.629247,
    "high": 0.643965,
    "low": 0.628756,
    "close": 0.643466,
    "volume": 0.0,
    "interval": "1h"
  },
  {
    "symbol": "ADA",
    "timestamp": "2025-03-01T02:00:00",
    "open": 0.643547,
    "high": 0.649179,
    "low": 0.638496,
    "close": 0.645323,
    "volume": 0.0,
    "interval": "1h"
  },
  {
    "symbol": "ADA",
    "timestamp": "2025-03-01T03:00:00",
    "open": 0.645377,
    "high": 0.64763,
    "low": 0.642136,
    "close": 0.645237,
    "volume": 0.0,
    "interval": "1h"
  },
  {
    "symbol": "ADA",
    "timestamp": "2025-03-01T04:00:00",
    "open": 0.645174,
    "high": 0.65494,
    "low": 0.643918,
    "close": 0.653643,
    "volume": 0.0,
    "interval": "1h"
  },
  {
    "symbol": "ADA",
    "timestamp": "2025-03-01T05:00:00",
    "open": 0.653606,
    "high": 0.653914,
    "low": 0.648818,
    "close": 0.650192,
    "volume": 0.0,
    "interval": "1h"
  },
  {
    "symbol": "ADA",
    "timestamp": "2025-03-01T06:00:00",
    "open": 0.650202,
    "high": 0.65149,
    "low": 0.643928,
    "close": 0.64674,
    "volume": 0.0,
    "interval": "1h"
  },
  {
    "symbol": "ADA",
    "timestamp": "2025-03-01T07:00:00",
    "open": 0.64673,
    "high": 0.647244,
    "low": 0.638968,
    "close": 0.639422,
    "volume": 0.0,
    "interval": "1h"
  },
  {
    "symbol": "ADA",
    "timestamp": "2025-03-01T08:00:00",
    "open": 0.639311,
    "high": 0.646803,
    "low": 0.639285,
    "close": 0.644782,
    "volume": 0.0,
    "interval": "1h"
  },
  {
    "symbol": "ADA",
    "timestamp": "2025-03-01T09:00:00",
    "open": 0.644814,
    "high": 0.649951,
    "low": 0.641642,
    "close": 0.644505,
    "volume": 0.0,
    "interval": "1h"
  },
  {
    "symbol": "ADA",
    "timestamp": "2025-03-01T10:00:00",
    "open": 0.644695,
    "high": 0.644703,
    "low": 0.636093,
    "close": 0.637681,
    "volume": 0.0,
    "interval": "1h"
  },
  {
    "symbol": "ADA",
    "timestamp": "2025-03-01T11:00:00",
    "open": 0.637651,
    "high": 0.638397,
    "low": 0.630644,
    "close": 0.636225,
    "volume": 0.0,
    "interval": "1h"
  },
  {
    "symbol": "ADA",
    "timestamp": "2025-03-01T12:00:00",
    "open": 0.636225,
    "high": 0.637313,
    "low": 0.631601,
    "close": 0.635059,
    "volume": 0.0,
    "interval": "1h"
  },
  {
    "symbol": "ADA",
    "timestamp": "2025-03-01T13:00:00",
    "open": 0.635055,
    "high": 0.637762,
    "low": 0.625273,
    "close": 0.628984,
    "volume": 0.0,
    "interval": "1h"
  },
  {
    "symbol": "ADA",
    "timestamp": "2025-03-01T14:00:00",
    "open": 0.629062,
    "high": 0.634045,
    "low": 0.628032,
    "close": 0.631277,
    "volume": 0.0,
    "interval": "1h"
  },
  {
    "symbol": "ADA",
    "timestamp": "2025-03-01T15:00:00",
    "open": 0.631367,
    "high": 0.635944,
    "low": 0.629421,
    "close": 0.634943,
    "volume": 0.0,
    "interval": "1h"
  },
  {
    "symbol": "ADA",
    "timestamp": "2025-03-01T16:00:00",
    "open": 0.635017,
    "high": 0.637849,
    "low": 0.63036,
    "close": 0.635766,
    "volume": 0.0,
    "interval": "1h"
  },
  {
    "symbol": "ADA",
    "timestamp": "2025-03-01T17:00:00",
    "open": 0.635653,
    "high": 0.635782,
    "low": 0.631228,
    "close": 0.633266,
    "volume": 0.0,
    "interval": "1h"
  },
  {
    "symbol": "ADA",
    "timestamp": "2025-03-01T18:00:00",
    "open": 0.633087,
    "high": 0.63879,
    "low": 0.630923,
    "close": 0.637296,
    "volume": 0.0,
    "interval": "1h"
  },
  {
    "symbol": "ADA",
    "timestamp": "2025-03-01T19:00:00",
    "open": 0.637225,
    "high": 0.64498,
    "low": 0.6361,
    "close": 0.644143,
    "volume": 0.0,
    "interval": "1h"
  },
  {
    "symbol": "ADA",
    "timestamp": "2025-03-01T20:00:00",
    "open": 0.644134,
    "high": 0.647909,
    "low": 0.641327,
    "close": 0.647908,
    "volume": 0.0,
    "interval": "1h"
  },
  {
    "symbol": "ADA",
    "timestamp": "2025-03-01T21:00:00",
    "open": 0.647909,
    "high": 0.671689,
    "low": 0.646553,
    "close": 0.668252,
    "volume": 0.0,
    "interval": "1h"
  },
  {
    "symbol": "ADA",
    "timestamp": "2025-03-01T22:00:00",
    "open": 0.668275,
    "high": 0.676765,
    "low": 0.660159,
    "close": 0.667466,
    "volume": 0.0,
    "interval": "1h"
  },
  {
    "symbol": "ADA",
    "timestamp": "2025-03-01T23:00:00",
    "open": 0.66748,
    "high": 0.668814,
    "low": 0.655622,
    "close": 0.659466,
    "volume": 0.0,
    "interval": "1h"
  },
  {
    "symbol": "ADA",
    "timestamp": "2025-03-02T00:00:00",
    "open": 0.659466,
    "high": 0.661099,
    "low": 0.654305,
    "close": 0.65681,
    "volume": 0.0,
    "interval": "1h"
  },
  {
    "symbol": "ADA",
    "timestamp": "2025-03-02T01:00:00",
    "open": 0.656905,
    "high": 0.662206,
    "low": 0.655245,
    "close": 0.660957,
    "volume": 0.0,
    "interval": "1h"
  },
  {
    "symbol": "ADA",
    "timestamp": "2025-03-02T02:00:00",
    "open": 0.660947,
    "high": 0.671831,
    "low": 0.66002,
    "close": 0.670633,
    "volume": 0.0,
    "interval": "1h"
  },
  {
    "symbol": "ADA",
    "timestamp": "2025-03-02T03:00:00",
    "open": 0.670624,
    "high": 0.676097,
    "low": 0.667964,
    "close": 0.672213,
    "volume": 0.0,
    "interval": "1h"
  },
  {
    "symbol": "ADA",
    "timestamp": "2025-03-02T04:00:00",
    "open": 0.672202,
    "high": 0.67429,
    "low": 0.661641,
    "close": 0.662559,
    "volume": 0.0,
    "interval": "1h"
  },
  {
    "symbol": "ADA",
    "timestamp": "2025-03-02T05:00:00",
    "open": 0.66255,
    "high": 0.664643,
    "low": 0.6603,
    "close": 0.662508,
    "volume": 0.0,
    "interval": "1h"
  },
  {
    "symbol": "ADA",
    "timestamp": "2025-03-02T06:00:00",
    "open": 0.662733,
    "high": 0.668858,
    "low": 0.659786,
    "close": 0.665368,
    "volume": 0.0,
    "interval": "1h"
  },
  {
    "symbol": "ADA",
    "timestamp": "2025-03-02T07:00:00",
    "open": 0.665455,
    "high": 0.669185,
    "low": 0.662767,
    "close": 0.663164,
    "volume": 0.0,
    "interval": "1h"
  },
  {
    "symbol": "ADA",
    "timestamp": "2025-03-02T08:00:00",
    "open": 0.663175,
    "high": 0.664407,
    "low": 0.660172,
    "close": 0.662102,
    "volume": 0.0,
    "interval": "1h"
  },
  {
    "symbol": "ADA",
    "timestamp": "2025-03-02T09:00:00",
    "open": 0.662061,
    "high": 0.668087,
    "low": 0.660664,
    "close": 0.666425,
    "volume": 0.0,
    "interval": "1h"
  },
  {
    "symbol": "ADA",
    "timestamp": "2025-03-02T10:00:00",
    "open": 0.666046,
    "high": 0.667942,
    "low": 0.661651,
    "close": 0.663697,
    "volume": 0.0,
    "interval": "1h"
  },
  {
    "symbol": "ADA",
    "timestamp": "2025-03-02T11:00:00",
    "open": 0.663771,
    "high": 0.665219,
    "low": 0.660378,
    "close": 0.662955,
    "volume": 0.0,
    "interval": "1h"
  },
  {
    "symbol": "ADA",
    "timestamp": "2025-03-02T12:00:00",
    "open": 0.662944,
    "high": 0.663088,
    "low": 0.656678,
    "close": 0.660029,
    "volume": 0.0,
    "interval": "1h"
  },
  {
    "symbol": "ADA",
    "timestamp": "2025-03-02T13:00:00",
    "open": 0.660094,
    "high": 0.660357,
    "low": 0.652128,
    "close": 0.65499,
    "volume": 0.0,
    "interval": "1h"
  },
  {
    "symbol": "ADA",
    "timestamp": "2025-03-02T14:00:00",
    "open": 0.654882,
    "high": 0.656107,
    "low": 0.646182,
    "close": 0.647584,
    "volume": 0.0,
    "interval": "1h"
  },
  {
    "symbol": "ADA",
    "timestamp": "2025-03-02T15:00:00",
    "open": 0.647647,
    "high": 0.898075,
    "low": 0.645052,
    "close": 0.865648,
    "volume": 0.0,
    "interval": "1h"
  },
  {
    "symbol": "ADA",
    "timestamp": "2025-03-02T16:00:00",
    "open": 0.866173,
    "high": 1.14745,
    "low": 0.865589,
    "close": 1.038167,
    "volume": 0.0,
    "interval": "1h"
  },
  {
    "symbol": "ADA",
    "timestamp": "2025-03-02T17:00:00",
    "open": 1.037983,
    "high": 1.10539,
    "low": 0.998917,
    "close": 1.03207,
    "volume": 0.0,
    "interval": "1h"
  },
  {
    "symbol": "ADA",
    "timestamp": "2025-03-02T18:00:00",
    "open": 1.032423,
    "high": 1.043721,
    "low": 0.982309,
    "close": 1.013595,
    "volume": 0.0,
    "interval": "1h"
  },
  {
    "symbol": "ADA",
    "timestamp": "2025-03-02T19:00:00",
    "open": 1.013957,
    "high": 1.048307,
    "low": 1.00771,
    "close": 1.040559,
    "volume": 0.0,
    "interval": "1h"
  },
  {
    "symbol": "ADA",
    "timestamp": "2025-03-02T20:00:00",
    "open": 1.040038,
    "high": 1.045864,
    "low": 1.019091,
    "close": 1.030924,
    "volume": 0.0,
    "interval": "1h"
  },
  {
    "symbol": "ADA",
    "timestamp": "2025-03-02T21:00:00",
    "open": 1.030765,
    "high": 1.092191,
    "low": 1.02836,
    "close": 1.051197,
    "volume": 0.0,
    "interval": "1h"
  },
  {
    "symbol": "ADA",
    "timestamp": "2025-03-02T22:00:00",
    "open": 1.051396,
    "high": 1.072251,
    "low": 1.033434,
    "close": 1.07007,
    "volume": 0.0,
    "interval": "1h"
  },
  {
    "symbol": "ADA",
    "timestamp": "2025-03-02T23:00:00",
    "open": 1.069985,
    "high": 1.14352,
    "low": 1.068857,
    "close": 1.13535,
    "volume": 0.0,
    "interval": "1h"
  },
  {
    "symbol": "ADA",
    "timestamp": "2025-03-03T00:00:00",
    "open": 1.13475,
    "high": 1.17373,
    "low": 1.08198,
    "close": 1.086343,
    "volume": 0.0,
    "interval": "1h"
  },
  {
    "symbol": "ADA",
    "timestamp": "2025-03-03T01:00:00",
    "open": 1.086438,
    "high": 1.10685,
    "low": 1.051469,
    "close": 1.082637,
    "volume": 0.0,
    "interval": "1h"
  },
  {
    "symbol": "ADA",
    "timestamp": "2025-03-03T02:00:00",
    "open": 1.082529,
    "high": 1.085448,
    "low": 1.042346,
    "close": 1.076309,
    "volume": 0.0,
    "interval": "1h"
  },
  {
    "symbol": "ADA",
    "timestamp": "2025-03-03T03:00:00",
    "open": 1.076296,
    "high": 1.079281,
    "low": 1.04998,
    "close": 1.070529,
    "volume": 0.0,
    "interval": "1h"
  },
  {
    "symbol": "ADA",
    "timestamp": "2025-03-03T04:00:00",
    "open": 1.070438,
    "high": 1.079937,
    "low": 1.05442,
    "close": 1.072763,
    "volume": 0.0,
    "interval": "1h"
  },
  {
    "symbol": "ADA",
    "timestamp": "2025-03-03T05:00:00",
    "open": 1.072725,
    "high": 1.07561,
    "low": 1.055089,
    "close": 1.060701,
    "volume": 0.0,
    "interval": "1h"
  },
  {
    "symbol": "ADA",
    "timestamp": "2025-03-03T06:00:00",
    "open": 1.06089,
    "high": 1.060986,
    "low": 0.993436,
    "close": 1.007591,
    "volume": 0.0,
    "interval": "1h"
  },
  {
    "symbol": "ADA",
    "timestamp": "2025-03-03T07:00:00",
    "open": 1.00716,
    "high": 1.019433,
    "low": 0.986487,
    "close": 1.013642,
    "volume": 0.0,
    "interval": "1h"
  },
  {
    "symbol": "ADA",
    "timestamp": "2025-03-03T08:00:00",
    "open": 1.013914,
    "high": 1.016636,
    "low": 0.934313,
    "close": 0.941852,
    "volume": 0.0,
    "interval": "1h"
  },
  {
    "symbol": "ADA",
    "timestamp": "2025-03-03T09:00:00",
    "open": 0.941875,
    "high": 0.968083,
    "low": 0.927055,
    "close": 0.955425,
    "volume": 0.0,
    "interval": "1h"
  },
  {
    "symbol": "ADA",
    "timestamp": "2025-03-03T10:00:00",
    "open": 0.952884,
    "high": 0.986206,
    "low": 0.949324,
    "close": 0.984573,
    "volume": 0.0,
    "interval": "1h"
  },
  {
    "symbol": "ADA",
    "timestamp": "2025-03-03T11:00:00",
    "open": 0.983749,
    "high": 0.985566,
    "low": 0.959267,
    "close": 0.964394,
    "volume": 0.0,
    "interval": "1h"
  },
  {
    "symbol": "ADA",
    "timestamp": "2025-03-03T12:00:00",
    "open": 0.964396,
    "high": 1.032653,
    "low": 0.96308,
    "close": 0.986755,
    "volume": 0.0,
    "interval": "1h"
  },
  {
    "symbol": "ADA",
    "timestamp": "2025-03-03T13:00:00",
    "open": 0.987136,
    "high": 1.020337,
    "low": 0.983165,
    "close": 1.005616,
    "volume": 0.0,
    "interval": "1h"
  },
  {
    "symbol": "ADA",
    "timestamp": "2025-03-03T14:00:00",
    "open": 1.005536,
    "high": 1.009631,
    "low": 0.931528,
    "close": 0.934476,
    "volume": 0.0,
    "interval": "1h"
  },
  {
    "symbol": "ADA",
    "timestamp": "2025-03-03T15:00:00",
    "open": 0.936265,
    "high": 0.973877,
    "low": 0.933636,
    "close": 0.958033,
    "volume": 0.0,
    "interval": "1h"
  },
  {
    "symbol": "ADA",
    "timestamp": "2025-03-03T16:00:00",
    "open": 0.958299,
    "high": 0.979291,
    "low": 0.957055,
    "close": 0.970339,
    "volume": 0.0,
    "interval": "1h"
  },
  {
    "symbol": "ADA",
    "timestamp": "2025-03-03T17:00:00",
    "open": 0.970225,
    "high": 0.988522,
    "low": 0.962418,
    "close": 0.969525,
    "volume": 0.0,
    "interval": "1h"
  },
  {
    "symbol": "ADA",
    "timestamp": "2025-03-03T18:00:00",
    "open": 0.969496,
    "high": 0.972214,
    "low": 0.886645,
    "close": 0.901091,
    "volume": 0.0,
    "interval": "1h"
  },
  {
    "symbol": "ADA",
    "timestamp": "2025-03-03T19:00:00",
    "open": 0.900839,
    "high": 0.9094,
    "low": 0.822889,
    "close": 0.836212,
    "volume": 0.0,
    "interval": "1h"
  },
  {
    "symbol": "ADA",
    "timestamp": "2025-03-03T20:00:00",
    "open": 0.836987,
    "high": 0.88057,
    "low": 0.835469,
    "close": 0.875227,
    "volume": 0.0,
    "interval": "1h"
  },
  {
    "symbol": "ADA",
    "timestamp": "2025-03-03T21:00:00",
    "open": 0.875173,
    "high": 0.878341,
    "low": 0.832277,
    "close": 0.836667,
    "volume": 0.0,
    "interval": "1h"
  },
  {
    "symbol": "ADA",
    "timestamp": "2025-03-03T22:00:00",
    "open": 0.836639,
    "high": 0.868421,
    "low": 0.836515,
    "close": 0.860073,
    "volume": 0.0,
    "interval": "1h"
  },
  {
    "symbol": "ADA",
    "timestamp": "2025-03-03T23:00:00",
    "open": 0.860084,
    "high": 0.870672,
    "low": 0.853919,
    "close": 0.857785,
    "volume": 0.0,
    "interval": "1h"
  },
  {
    "symbol": "ADA",
    "timestamp": "2025-03-04T00:00:00",
    "open": 0.857594,
    "high": 0.863476,
    "low": 0.822323,
    "close": 0.825957,
    "volume": 0.0,
    "interval": "1h"
  },
  {
    "symbol": "ADA",
    "timestamp": "2025-03-04T01:00:00",
    "open": 0.825547,
    "high": 0.830219,
    "low": 0.77355,
    "close": 0.785049,
    "volume": 0.0,
    "interval": "1h"
  },
  {
    "symbol": "ADA",
    "timestamp": "2025-03-04T02:00:00",
    "open": 0.78528,
    "high": 0.802,
    "low": 0.757829,
    "close": 0.79157,
    "volume": 0.0,
    "interval": "1h"
  },
  {
    "symbol": "ADA",
    "timestamp": "2025-03-04T03:00:00",
    "open": 0.791756,
    "high": 0.813351,
    "low": 0.783501,
    "close": 0.800546,
    "volume": 0.0,
    "interval": "1h"
  },
  {
    "symbol": "ADA",
    "timestamp": "2025-03-04T04:00:00",
    "open": 0.800546,
    "high": 0.808595,
    "low": 0.793356,
    "close": 0.796713,
    "volume": 0.0,
    "interval": "1h"
  },
  {
    "symbol": "ADA",
    "timestamp": "2025-03-04T05:00:00",
    "open": 0.796874,
    "high": 0.833559,
    "low": 0.795246,
    "close": 0.82345,
    "volume": 0.0,
    "interval": "1h"
  },
  {
    "symbol": "ADA",
    "timestamp": "2025-03-04T06:00:00",
    "open": 0.823657,
    "high": 0.831999,
    "low": 0.806042,
    "close": 0.810141,
    "volume": 0.0,
    "interval": "1h"
  },
  {
    "symbol": "ADA",
    "timestamp": "2025-03-04T07:00:00",
    "open": 0.810044,
    "high": 0.821855,
    "low": 0.800903,
    "close": 0.808508,
    "volume": 0.0,
    "interval": "1h"
  },
  {
    "symbol": "ADA",
    "timestamp": "2025-03-04T08:00:00",
    "open": 0.808505,
    "high": 0.827462,
    "low": 0.800881,
    "close": 0.815159,
    "volume": 0.0,
    "interval": "1h"
  },
  {
    "symbol": "ADA",
    "timestamp": "2025-03-04T09:00:00",
    "open": 0.815149,
    "high": 0.816824,
    "low": 0.795962,
    "close": 0.807305,
    "volume": 0.0,
    "interval": "1h"
  },
  {
    "symbol": "ADA",
    "timestamp": "2025-03-04T10:00:00",
    "open": 0.807196,
    "high": 0.826417,
    "low": 0.800482,
    "close": 0.821014,
    "volume": 0.0,
    "interval": "1h"
  },
  {
    "symbol": "ADA",
    "timestamp": "2025-03-04T11:00:00",
    "open": 0.820912,
    "high": 0.83602,
    "low": 0.812268,
    "close": 0.813543,
    "volume": 0.0,
    "interval": "1h"
  },
  {
    "symbol": "ADA",
    "timestamp": "2025-03-04T12:00:00",
    "open": 0.813432,
    "high": 0.81768,
    "low": 0.802406,
    "close": 0.805996,
    "volume": 0.0,
    "interval": "1h"
  },
  {
    "symbol": "ADA",
    "timestamp": "2025-03-04T13:00:00",
    "open": 0.805885,
    "high": 0.807176,
    "low": 0.78188,
    "close": 0.796961,
    "volume": 0.0,
    "interval": "1h"
  },
  {
    "symbol": "ADA",
    "timestamp": "2025-03-04T14:00:00",
    "open": 0.797081,
    "high": 0.909618,
    "low": 0.792291,
    "close": 0.820536,
    "volume": 0.0,
    "interval": "1h"
  },
  {
    "symbol": "ADA",
    "timestamp": "2025-03-04T15:00:00",
    "open": 0.82075,
    "high": 0.854607,
    "low": 0.794849,
    "close": 0.853873,
    "volume": 0.0,
    "interval": "1h"
  },
  {
    "symbol": "ADA",
    "timestamp": "2025-03-04T16:00:00",
    "open": 0.854171,
    "high": 0.879166,
    "low": 0.82339,
    "close": 0.872941,
    "volume": 0.0,
    "interval": "1h"
  },
  {
    "symbol": "ADA",
    "timestamp": "2025-03-04T17:00:00",
    "open": 0.873193,
    "high": 0.952026,
    "low": 0.865057,
    "close": 0.926235,
    "volume": 0.0,
    "interval": "1h"
  },
  {
    "symbol": "ADA",
    "timestamp": "2025-03-04T18:00:00",
    "open": 0.925901,
    "high": 0.944486,
    "low": 0.903807,
    "close": 0.93997,
    "volume": 0.0,
    "interval": "1h"
  },
  {
    "symbol": "ADA",
    "timestamp": "2025-03-04T19:00:00",
    "open": 0.939828,
    "high": 0.955878,
    "low": 0.919375,
    "close": 0.925747,
    "volume": 0.0,
    "interval": "1h"
  },
  {
    "symbol": "ADA",
    "timestamp": "2025-03-04T20:00:00",
    "open": 0.925697,
    "high": 0.93695,
    "low": 0.903599,
    "close": 0.907692,
    "volume": 0.0,
    "interval": "1h"
  },
  {
    "symbol": "ADA",
    "timestamp": "2025-03-04T21:00:00",
    "open": 0.907907,
    "high": 0.954402,
    "low": 0.906218,
    "close": 0.944,
    "volume": 0.0,
    "interval": "1h"
  },
  {
    "symbol": "ADA",
    "timestamp": "2025-03-04T22:00:00",
    "open": 0.944476,
    "high": 0.955555,
    "low": 0.92602,
    "close": 0.928303,
    "volume": 0.0,
    "interval": "1h"
  },
  {
    "symbol": "ADA",
    "timestamp": "2025-03-04T23:00:00",
    "open": 0.928377,
    "high": 0.949492,
    "low": 0.927808,
    "close": 0.940822,
    "volume": 0.0,
    "interval": "1h"
  },
  {
    "symbol": "ADA",
    "timestamp": "2025-03-05T00:00:00",
    "open": 0.940721,
    "high": 0.972156,
    "low": 0.926822,
    "close": 0.943319,
    "volume": 0.0,
    "interval": "1h"
  }
]